MANIFEST.in
setup.py
eclectica/__init__.py
eclectica/main.py
eclectica.egg-info/PKG-INFO
eclectica.egg-info/SOURCES.txt
eclectica.egg-info/dependency_links.txt
eclectica.egg-info/entry_points.txt
eclectica.egg-info/not-zip-safe
eclectica.egg-info/top_level.txt
scripts/install.sh