Metadata-Version: 1.0
Name: eclectica
Version: 0.7.1
Summary: Cool and eclectic version manager for any language
Home-page: https://github.com/markelog/eclectica
Author: Oleg Gaidarenko
Author-email: markelog@gmail.com
License: MIT
Keywords: eclectica,version,manager,binary,environment
Platform: UNKNOWN
